geometry_calculator/__init__.py
geometry_calculator/factory/__init__.py
geometry_calculator/factory/figure_factory.py
geometry_calculator/figure/__init__.py
geometry_calculator/figure/circle.py
geometry_calculator/figure/ifigure.py
geometry_calculator/figure/triangle.py
ruvik_geometry_calculator-1.0.0.dist-info/METADATA
ruvik_geometry_calculator-1.0.0.dist-info/WHEEL
ruvik_geometry_calculator-1.0.0.dist-info/tmptm0np2ml
ruvik_geometry_calculator-1.0.0.dist-info/top_level.txt
ruvik_geometry_calculator-1.0.0.dist-info/RECORD
