Metadata-Version: 2.1
Name: ruvik-geometry-calculator
Version: 1.0.0
Summary: Библиотека для вычисления площади геометрических фигур
Author: Rudnev Viktor
Author-email: rudnevvictor2003@mail.ru
Classifier: Programming Language :: Python :: 3
Classifier: Operating System :: OS Independent
Requires-Python: >=3.6
Provides-Extra: test
Requires-Dist: pytest >=6.0 ; extra == 'test'
Requires-Dist: pytest-cov >=2.0 ; extra == 'test'
Requires-Dist: coverage >=5.0 ; extra == 'test'
